Topsis_KrishnaVig_102217119/__init__.py
Topsis_KrishnaVig_102217119/__main__.py
Topsis_KrishnaVig_102217119/topsis.py
Topsis_KrishnaVig_102217119-1.0.14.dist-info/METADATA
Topsis_KrishnaVig_102217119-1.0.14.dist-info/WHEEL
Topsis_KrishnaVig_102217119-1.0.14.dist-info/entry_points.txt
Topsis_KrishnaVig_102217119-1.0.14.dist-info/top_level.txt
Topsis_KrishnaVig_102217119-1.0.14.dist-info/RECORD
