Metadata-Version: 2.2
Name: Topsis_KrishnaVig_102217119
Version: 1.0.14
Summary: A python package for implementing topsis
Home-page: https://github.com/vigkrishna/Topsis_102217119
Author: Krishna Vig
Author-email: kvig1_be22@thapar.com
Classifier: Programming Language :: Python :: 3
Classifier: License :: OSI Approved :: MIT License
Classifier: Operating System :: OS Independent
Requires-Dist: pandas
Requires-Dist: numpy
Dynamic: author
Dynamic: author-email
Dynamic: classifier
Dynamic: description
Dynamic: description-content-type
Dynamic: home-page
Dynamic: requires-dist
Dynamic: summary
